Metadata-Version: 2.1
Name: pyecore-py2
Version: 0.9.0
Summary: A Python(ic) Implementation of the Eclipse Modeling Framework (EMF/Ecore), Python 2.7 backport
Home-page: https://github.com/pyecore/pyecore-py2
Author: Vincent Aranega
Author-email: vincent.aranega@gmail.com
License: BSD 3-Clause
Keywords: model metamodel EMF Ecore MDE
Platform: UNKNOWN
Classifier: Development Status :: 4 - Beta
Classifier: Programming Language :: Python
Classifier: Programming Language :: Python :: 2.7
Classifier: Operating System :: OS Independent
Classifier: Intended Audience :: Developers
Classifier: Topic :: Software Development
Classifier: Topic :: Software Development :: Libraries
Classifier: License :: OSI Approved :: BSD License
Requires-Dist: enum34
Requires-Dist: chainmap
Requires-Dist: backports.functools-lru-cache
Requires-Dist: ordered-set
Requires-Dist: singledispatch
Requires-Dist: lxml
Requires-Dist: defusedxml
Requires-Dist: restrictedpython (>=4.0b6)
